jms/auth.py
jms/service.py
jms/tasks.py
jms/config.py
jms/compat.py
jms/mixin.py
jms/__init__.py
jms/api.py
jms/utils.py
jms/authentication.py
jms/exceptions.py
jumpserver_python_sdk-0.0.16.dist-info/RECORD
jumpserver_python_sdk-0.0.16.dist-info/metadata.json
jumpserver_python_sdk-0.0.16.dist-info/WHEEL
jumpserver_python_sdk-0.0.16.dist-info/DESCRIPTION.rst
jumpserver_python_sdk-0.0.16.dist-info/pbr.json
jumpserver_python_sdk-0.0.16.dist-info/top_level.txt
jumpserver_python_sdk-0.0.16.dist-info/METADATA
