Metadata-Version: 2.0
Name: jumpserver-python-sdk
Version: 0.0.16
Summary: Jumpserver python sdk tools
Home-page: http://jumpserver.org
Author: Jumpserver team
Author-email: ibuler@qq.com
License: UNKNOWN
Keywords: jms jumpserver
Platform: UNKNOWN
Classifier: Development Status :: 5 - Production/Stable
Classifier: Intended Audience :: Developers
Classifier: License :: OSI Approved :: MIT License
Classifier: Operating System :: OS Independent
Classifier: Programming Language :: Python
Classifier: Programming Language :: Python :: 3.5
Classifier: Programming Language :: Python :: 3.6
Requires-Dist: dotmap (>=1.2.14)
Requires-Dist: paramiko (>=2.1.1)
Requires-Dist: requests (>=2.11.1)
Requires-Dist: cachetools (>=2.0.0)
Requires-Dist: pytz (==2017.2)
Requires-Dist: pyte (==0.5.2)
